<template>'Computer'<textbox><dimension><height>9.95</height><width>4.95</width><xpos>10px</xpos><ypos>15px</ypos></dimension><border><bordercolor>black</bordercolor><borderwidth>1px</borderwidth><borderstyle>solid</borderstyle></border><text></text><bgcolor> </bgcolor><bgimage></bgimage></textbox><textbox><dimension><height>9.95</height><width>4.95</width><xpos>10px</xpos><ypos>15px</ypos></dimension><border><bordercolor>black</bordercolor><borderwidth>1px</borderwidth><borderstyle>solid</borderstyle></border><text><P><STRONG>COMPUTER&nbsp;&nbsp;&nbsp;&nbsp;&nbsp;&nbsp;&nbsp;&nbsp;&nbsp;&nbsp;&nbsp;&nbsp;PROBLEM?</STRONG>&nbsp;&nbsp;&nbsp;&nbsp;&nbsp;&nbsp;&nbsp;&nbsp;&nbsp;&nbsp;&nbsp;&nbsp;&nbsp;&nbsp;<STRONG> NO PROBLEM CONTACT US FOR</STRONG></P></text><bgcolor> </bgcolor><bgimage></bgimage></textbox><textbox><dimension><height>9.95</height><width>4.95</width><xpos>10px</xpos><ypos>137px</ypos></dimension><border><bordercolor>black</bordercolor><borderwidth>1px</borderwidth><borderstyle>solid</borderstyle></border><text>Assembling of New Computer&nbsp;&nbsp;&nbsp; -Sale/Purchase of old computer&nbsp;&nbsp; -Hardware Troubleshooting.&nbsp;&nbsp;&nbsp;&nbsp;&nbsp;&nbsp;&nbsp;&nbsp; -Software Installation.&nbsp;&nbsp;&nbsp;&nbsp;&nbsp;&nbsp;&nbsp;&nbsp;&nbsp;&nbsp;&nbsp;&nbsp;&nbsp;&nbsp;&nbsp;&nbsp;&nbsp;&nbsp;&nbsp;&nbsp;&nbsp; -AMC Contract&nbsp;&nbsp;&nbsp;&nbsp;&nbsp;&nbsp;&nbsp;&nbsp;&nbsp;&nbsp;&nbsp;&nbsp;&nbsp;&nbsp;&nbsp;&nbsp;&nbsp;&nbsp;&nbsp;&nbsp;&nbsp;&nbsp;&nbsp;&nbsp;&nbsp;&nbsp;&nbsp;&nbsp;&nbsp;&nbsp;&nbsp;&nbsp;&nbsp;&nbsp; -Cartridge Refilling&nbsp;&nbsp;&nbsp;&nbsp;&nbsp;&nbsp;&nbsp;&nbsp;&nbsp;&nbsp;&nbsp;&nbsp;&nbsp;&nbsp;&nbsp;&nbsp;&nbsp;&nbsp;&nbsp;&nbsp;&nbsp;&nbsp;&nbsp;&nbsp;&nbsp; -Computer Repearing</text><bgcolor> </bgcolor><bgimage></bgimage></textbox></template>
